simplelogger/__init__.py
simplelogger/_data/Hack-Bold.woff2
simplelogger/_data/Hack-BoldItalic.woff2
simplelogger/_data/Hack-Italic.woff2
simplelogger/_data/Hack-Regular.woff2
simplelogger/_data/Monoid.woff2
simplelogger/_data/ShareTechMono.woff2
simplelogger/_data/css_template.css
simplelogger/_data/hack-bold-italic.ttf
simplelogger/_data/hack-bold.ttf
simplelogger/_data/hack-italic.ttf
simplelogger/_data/hack-regular.ttf
simplelogger/_data/html-themes.json
simplelogger/_data/html_template.html
simplelogger/_data/js/htmlFormat.js
simplelogger/_data/js/printFormat.js
simplelogger/constants.py
simplelogger/html.py
simplelogger/pdf.py
bb_simplelogger-0.1.0.dist-info/METADATA
bb_simplelogger-0.1.0.dist-info/WHEEL
bb_simplelogger-0.1.0.dist-info/RECORD
