Metadata-Version: 2.1
Name: bb-simplelogger
Version: 0.1.0
Summary: Custom logger class using the builtin logging module
Author: Erik Beebe
Author-email: beebeapps_debugging@tuta.io
Requires-Python: >=3.12,<4.0
Classifier: Programming Language :: Python :: 3
Classifier: Programming Language :: Python :: 3.12
